README.txt
dingus.py
setup.py
dingus.egg-info/PKG-INFO
dingus.egg-info/SOURCES.txt
dingus.egg-info/dependency_links.txt
dingus.egg-info/top_level.txt