Metadata-Version: 1.0
Name: dingus
Version: 0.3.4
Summary: A record-then-assert mocking library
Home-page: https://github.com/garybernhardt/dingus
Author: Gary Bernhardt
Author-email: gary.bernhardt@gmail.com
License: MIT
Keywords: testing test mocking mock double stub fake record assert
Platform: UNKNOWN
Classifier: Development Status :: 4 - Beta
Classifier: Intended Audience :: Developers
Classifier: License :: OSI Approved :: MIT License
Classifier: Operating System :: OS Independent
Classifier: Programming Language :: Python
Classifier: Topic :: Software Development :: Testing
